{
    "$schema": "https://schema.management.azure.com/schemas/2019-04-01/deploymentTemplate.json#",
    "contentVersion": "1.0.0.0",
    "parameters": {
        "workspace": {
            "type": "String"
        }
    },
    "resources": [
      {
        "id": "[concat(resourceId('Microsoft.OperationalInsights/workspaces/providers', parameters('workspace'), 'Microsoft.SecurityInsights'),'/alertRules/4ecd8c1f-a7d3-4b56-86fa-b6c095baa28b')]",
        "name": "[concat(parameters('workspace'),'/Microsoft.SecurityInsights/4ecd8c1f-a7d3-4b56-86fa-b6c095baa28b')]",
        "type": "Microsoft.OperationalInsights/workspaces/providers/alertRules",
        "kind": "MicrosoftSecurityIncidentCreation",
        "apiVersion": "2022-09-01-preview",
        "properties": {
          "displayName": "Valid Analytics Rule - 4ecd8c1f-a7d3-4b56-86fa-b6c095baa28b",
          "description": "Create incidents based on all alerts generated in Microsoft 365 Insider Risk Management",
          "enabled": true,
          "severitiesFilter": null,
          "displayNamesFilter": null,
          "displayNamesExcludeFilter": null,
          "alertRuleTemplateName": null
        }
      }
    ]
}
