{
  "$schema": "https://schema.management.azure.com/schemas/2019-04-01/deploymentTemplate.json#",
  "contentVersion": "1.0.0.0",
  "parameters": {
    "workspace": {
      "type": "String"
    }
  },
  "resources": [
    {
      "id": "[concat(resourceId('Microsoft.OperationalInsights/workspaces/providers', parameters('workspace'), 'Microsoft.SecurityInsights'),'/alertRules/9ed6a91b-8251-4b77-91a5-bbcb50e217b8')]",
      "name": "[concat(parameters('workspace'),'/Microsoft.SecurityInsights/9ed6a91b-8251-4b77-91a5-bbcb50e217b8')]",
      "type": "Microsoft.OperationalInsights/workspaces/providers/alertRules",
      "kind": "Scheduled",
      "apiVersion": "2021-03-01-preview",
      "properties": {
        "displayName": "Valid Analytic Rule 1 - 9ed6a91b-8251-4b77-91a5-bbcb50e217b8",
        "description": "DESCRIPTION CHECK",
        "severity": "High",
        "enabled": true,
        "query": "SecurityAlert",
        "queryFrequency": "PT5H",
        "queryPeriod": "PT5H",
        "triggerOperator": "GreaterThan",
        "triggerThreshold": 0,
        "suppressionDuration": "PT5H",
        "suppressionEnabled": false,
        "tactics": [],
        "alertRuleTemplateName": null,
        "incidentConfiguration": {
          "createIncident": true,
          "groupingConfiguration": {
            "enabled": false,
            "reopenClosedIncident": false,
            "lookbackDuration": "PT5H",
            "matchingMethod": "AllEntities",
            "groupByEntities": [],
            "groupByAlertDetails": [],
            "groupByCustomDetails": []
          }
        },
        "eventGroupingSettings": {
          "aggregationKind": "SingleAlert"
        },
        "alertDetailsOverride": {
          "alertDisplayNameFormat": "alert name {{AlertName}}",
          "alertDescriptionFormat": "DESC test {{Description}}",
          "alertTacticsColumnName": null,
          "alertSeverityColumnName": null
        },
        "customDetails": null,
        "entityMappings": null
      }
    }
  ]
}
